setuppycheck.py
setuppycheck-0.0.1.dist-info/DESCRIPTION.rst
setuppycheck-0.0.1.dist-info/entry_points.txt
setuppycheck-0.0.1.dist-info/METADATA
setuppycheck-0.0.1.dist-info/metadata.json
setuppycheck-0.0.1.dist-info/pbr.json
setuppycheck-0.0.1.dist-info/RECORD
setuppycheck-0.0.1.dist-info/top_level.txt
setuppycheck-0.0.1.dist-info/WHEEL
