Metadata-Version: 2.0
Name: setuppycheck
Version: 0.0.1
Summary: Checks for questionable practices in setup.py files.
Home-page: https://github.com/msabramo/setuppycheck
Author: Marc Abramowitz
Author-email: msabramo@gmail.com
License: MIT
Keywords: setup.py pin dependencies
Platform: UNKNOWN
Requires-Dist: mock
